th2_cli/__init__.py
th2_cli/__main__.py
th2_cli/cli/__init__.py
th2_cli/cli/delete.py
th2_cli/cli/install.py
th2_cli/cli/mgr/__init__.py
th2_cli/cli/mgr/logs.py
th2_cli/cli/mgr/status.py
th2_cli/cli/status.py
th2_cli/cli/version.py
th2_cli/templates/__init__.py
th2_cli/templates/install/__init__.py
th2_cli/templates/install/pvcs.py
th2_cli/templates/install/pvs.py
th2_cli/templates/install/values/__init__.py
th2_cli/templates/install/values/ingress.py
th2_cli/templates/install/values/loki.py
th2_cli/templates/install/values/prometheus_operator.py
th2_cli/templates/install/values/secrets.py
th2_cli/templates/install/values/service.py
th2_cli/utils/__init__.py
th2_cli/utils/cassandra.py
th2_cli/utils/crypto.py
th2_cli/utils/helm/__init__.py
th2_cli/utils/helm/charts_installer.py
th2_cli/utils/infra.py
th2_cli/utils/install_config/__init__.py
th2_cli/utils/install_config/cassandra.py
th2_cli/utils/install_config/infra_mgr/__init__.py
th2_cli/utils/install_config/infra_mgr/git.py
th2_cli/utils/install_config/kubernetes.py
th2_cli/utils/kubernetes.py
th2_cli-1.7.3.dist-info/entry_points.txt
th2_cli-1.7.3.dist-info/LICENSE
th2_cli-1.7.3.dist-info/WHEEL
th2_cli-1.7.3.dist-info/METADATA
th2_cli-1.7.3.dist-info/RECORD
